findref/__init__.py
findref/_version.py
findref/api.py
findref/cache.py
findref/cli.py
findref/models.py
findref/paths.py
findref/ui.py
findref/docs/__init__.py
findref/tests/__init__.py
findref/tests/helper.py
findref/vendor/__init__.py
findref/vendor/pytest_cov_helper.py
findref-0.2.2.dist-info/AUTHORS.rst
findref-0.2.2.dist-info/LICENSE.txt
findref-0.2.2.dist-info/METADATA
findref-0.2.2.dist-info/WHEEL
findref-0.2.2.dist-info/entry_points.txt
findref-0.2.2.dist-info/top_level.txt
findref-0.2.2.dist-info/RECORD
